SearchEngine/DataManage.py
SearchEngine/__init__.py
SearchEngine/__version__.py
FindEngine-0.0.2.dist-info/LICENSE
FindEngine-0.0.2.dist-info/METADATA
FindEngine-0.0.2.dist-info/WHEEL
FindEngine-0.0.2.dist-info/top_level.txt
FindEngine-0.0.2.dist-info/RECORD
