Metadata-Version: 2.1
Name: FindEngine
Version: 0.0.2
Summary: SearchEngine——Global Search,Global-SearchEngine
Home-page: https://github.com/AndersonHJB/SearchEngine
Author: Bornforthis
Author-email: aiyuechuang@gmail.com
License: MIT
Classifier: License :: OSI Approved :: MIT License
Classifier: Programming Language :: Python
Classifier: Programming Language :: Python :: 3
Classifier: Programming Language :: Python :: 3.6
Classifier: Programming Language :: Python :: Implementation :: CPython
Classifier: Programming Language :: Python :: Implementation :: PyPy
Requires-Python: >=3.6.0
License-File: LICENSE
